README.md
setup.py
asynci_box/__init__.py
asynci_box/compat.py
asynci_box/context.py
asynci_box/defer.py
asynci_box/fork.py
asynci_box/func.py
asynci_box/iter.py
asynci_box/server.py
asynci_box/timer.py
asynci_box.egg-info/PKG-INFO
asynci_box.egg-info/SOURCES.txt
asynci_box.egg-info/dependency_links.txt
asynci_box.egg-info/top_level.txt