Metadata-Version: 2.1
Name: asynci-box
Version: 1.4.7
Summary: Idiomatic asyncio utilities
Home-page: https://github.com/achimnol/aiotools
Author: Joongi Kim
Author-email: me@daybreaker.info
License: apache2
Platform: UNKNOWN
Classifier: Programming Language :: Python :: 3.8
Classifier: Programming Language :: Python :: 3.9
Classifier: Programming Language :: Python :: 3.10
Classifier: License :: OSI Approved :: Apache Software License
Requires-Python: >=3.6, <=3.11
